sbenchmark_dependency_test_two/__init__.py
sbenchmark_dependency_test_two-1.0.2.dist-info/METADATA
sbenchmark_dependency_test_two-1.0.2.dist-info/WHEEL
sbenchmark_dependency_test_two-1.0.2.dist-info/top_level.txt
sbenchmark_dependency_test_two-1.0.2.dist-info/RECORD
