Metadata-Version: 2.4
Name: sbenchmark-dependency-test-two
Version: 1.0.2
Summary: Python test library to be used with sbenchmark suite to provide testable version numbers.
Author: Felix Reichmann
Keywords: dependency,sbenchmark,testpypi
Classifier: Programming Language :: Python :: 3
Classifier: Programming Language :: Python :: 3 :: Only
Classifier: License :: OSI Approved :: MIT License
Classifier: Operating System :: OS Independent
Requires-Python: >=3.12
Requires-Dist: sbenchmark-dependency-test-one==1.0.2
